setup.py
pkg5/__init__.py
pkg5/cycle.py
pkg5.egg-info/PKG-INFO
pkg5.egg-info/SOURCES.txt
pkg5.egg-info/dependency_links.txt
pkg5.egg-info/top_level.txt