Metadata-Version: 2.1
Name: pkg5
Version: 0.1.0
Summary: A example Python package
Home-page: https://github.com/el-0mbre
Author: Stanislav Efimtsev
Author-email: evendot@yandex.ru
License: BSD 2-clause
Platform: UNKNOWN
Classifier: Development Status :: 1 - Planning
Classifier: Intended Audience :: Science/Research
Classifier: License :: OSI Approved :: BSD License
Classifier: Operating System :: POSIX :: Linux
Classifier: Programming Language :: Python :: 3.5
